pg_redis/__init__.py
pg_redis/define.py
pg_redis/redis.py
pg_redis-1.0.8.dist-info/METADATA
pg_redis-1.0.8.dist-info/WHEEL
pg_redis-1.0.8.dist-info/top_level.txt
pg_redis-1.0.8.dist-info/RECORD
