Metadata-Version: 2.1
Name: pg_redis
Version: 1.0.8
Summary: python game: redis
Author: baozilaji@gmail.com
Requires-Python: >=3.9
Requires-Dist: pg-environment
